README.md
setup.cfg
setup.py
yandex_translate_api/__init__.py
yandex_translate_api.egg-info/PKG-INFO
yandex_translate_api.egg-info/SOURCES.txt
yandex_translate_api.egg-info/dependency_links.txt
yandex_translate_api.egg-info/requires.txt
yandex_translate_api.egg-info/top_level.txt