Metadata-Version: 1.0
Name: yandex-translate-api
Version: 1.1
Summary: Перевод текст через API Yandex
Home-page: UNKNOWN
Author: UNKNOWN
Author-email: cklfgads@knowledgemd.com
License: UNKNOWN
Platform: UNKNOWN
